setup.cfg
setup.py
frenetic/__init__.py
frenetic/net_utils.py
frenetic/packet.py
frenetic/syntax.py
frenetic.egg-info/PKG-INFO
frenetic.egg-info/SOURCES.txt
frenetic.egg-info/dependency_links.txt
frenetic.egg-info/requires.txt
frenetic.egg-info/top_level.txt