Metadata-Version: 1.0
Name: frenetic
Version: 4.1.0
Summary: Python bindings for Frenetic
Home-page: https://github.com/frenetic-lang/frenetic
Author: Arjun Guha
Author-email: arjun@cs.umass.edu
License: UNKNOWN
Platform: UNKNOWN
